{
  "version": "3.4",
  "log": [
    {
      "contracts/Box.sol:Box": {
        "src": "contracts\\Box.sol:5",
        "version": {
          "withMetadata": "e4a9ce291d3bf30dfd92cf83d4d4f5ce5b77439781d616b05738a3fdb65897f4",
          "withoutMetadata": "cba9f8cf52e3c449631a04ea218a6cedcaf7c366669cfc257c89a008266c768f",
          "linkedWithoutMetadata": "cba9f8cf52e3c449631a04ea218a6cedcaf7c366669cfc257c89a008266c768f"
        },
        "inherit": [],
        "libraries": [],
        "methods": [
          "store(uint256)",
          "retrieve()"
        ],
        "linkReferences": [],
        "errors": [],
        "layout": {
          "storage": [
            {
              "label": "value",
              "offset": 0,
              "slot": "0",
              "type": "t_uint256",
              "contract": "Box",
              "src": "contracts\\Box.sol:6"
            }
          ],
          "types": {
            "t_uint256": {
              "label": "uint256",
              "numberOfBytes": "32"
            }
          },
          "layoutVersion": "1.2",
          "flat": true
        },
        "solcVersion": "0.8.17"
      }
    }
  ]
}